CHANGES.txt
MANIFEST.in
README.txt
dev_requirements.txt
setup.py
lubdub/__init__.py
lubdub/analyze.py
lubdub/calc.py
lubdub/exceptions.py
lubdub/graph.py
lubdub/load.py
lubdub.egg-info/PKG-INFO
lubdub.egg-info/SOURCES.txt
lubdub.egg-info/dependency_links.txt
lubdub.egg-info/not-zip-safe
lubdub.egg-info/top_level.txt
tests/__init__.py
tests/real_data.py
tests/test_calc.py
tests/test_graph.py
tests/test_measurement.py