Metadata-Version: 1.0
Name: lubdub
Version: 0.0.2.1
Summary: ECG/EKG, RR, NN, HRV, and heartrate calculation toolkit
Home-page: https://bitbucket.org/nthmost/lubdub
Author: Naomi Most
Author-email: naomi@corewellness.io
License: Apache 2.0
Platform: UNKNOWN
